zdx/__init__.py
zdx/cli.py
zdx/scripts/__init__.py
zdx/scripts/gen_api.py
zdx/scripts/gen_readmes.py
zdx-0.2.0.dev4.dist-info/LICENSE
zdx-0.2.0.dev4.dist-info/METADATA
zdx-0.2.0.dev4.dist-info/WHEEL
zdx-0.2.0.dev4.dist-info/entry_points.txt
zdx-0.2.0.dev4.dist-info/RECORD
