Metadata-Version: 2.3
Name: zdx
Version: 0.2.0.dev4
Summary: Z Doc Builder Experience by Swarmauri
License: Apache-2.0
Keywords: mkdocs,documentation,swarmauri,docs,doc builder
Author: Jacob Stewart
Author-email: jacob@swarmauri.com
Requires-Python: >=3.12,<3.13
Classifier: License :: OSI Approved :: Apache Software License
Classifier: Programming Language :: Python :: 3
Classifier: Programming Language :: Python :: 3.12
Requires-Dist: griffe-typingdoc
Requires-Dist: mkdocs
Requires-Dist: mkdocs-autorefs
Requires-Dist: mkdocs-gen-files
Requires-Dist: mkdocs-literate-nav
Requires-Dist: mkdocs-material (>=9.6.4,<10.0.0)
Requires-Dist: mkdocstrings[python] (>=0.28.1,<0.29.0)
Requires-Dist: pyyaml (>=6.0)
Requires-Dist: ruff (>=0.5)
